q1simulator/Qblox_QCM_pulse_response.hdf5
q1simulator/__init__.py
q1simulator/analogue_filter.py
q1simulator/channel_data.py
q1simulator/cluster.py
q1simulator/q1core.py
q1simulator/q1module.py
q1simulator/q1parser.py
q1simulator/q1plotter.py
q1simulator/q1sequencer.py
q1simulator/q1simulator.py
q1simulator/q1viewer.py
q1simulator/qblox_version.py
q1simulator/rt_renderer.py
q1simulator/trigger_sorting.py
q1simulator/triggers.py
q1simulator/gui/__init__.py
q1simulator/gui/program_browser.py
q1simulator/gui/program_details.py
q1simulator/gui/program_plotter.py
q1simulator/gui/qt_utils.py
q1simulator-1.0.5.dist-info/licenses/LICENSE
q1simulator-1.0.5.dist-info/METADATA
q1simulator-1.0.5.dist-info/WHEEL
q1simulator-1.0.5.dist-info/top_level.txt
q1simulator-1.0.5.dist-info/RECORD
