Metadata-Version: 2.4
Name: q1simulator
Version: 1.0.5
Summary: Simulator for Qblox Q1ASM simulating QCM and QRM modules and plotting output.
Author-email: Sander de Snoo <s.l.desnoo@tudelft.nl>
License-Expression: MIT
Project-URL: Documentation, https://github.com/sldesnoo-Delft/q1simulator/blob/main/README.md
Project-URL: Repository, https://github.com/sldesnoo-Delft/q1simulator
Project-URL: Changelog, https://github.com/sldesnoo-Delft/q1simulator/blob/main/CHANGELOG.md
Classifier: Programming Language :: Python :: 3
Classifier: Operating System :: OS Independent
Requires-Python: >=3.10
License-File: LICENSE
Requires-Dist: qcodes
Requires-Dist: qblox_instruments
Requires-Dist: numpy
Requires-Dist: matplotlib
Requires-Dist: qtpy
Requires-Dist: pyqtgraph
Dynamic: license-file
